{
  "context": {
    "date": "2020-03-01 23:19:26",
    "host_name": "dyarosh-u",
    "executable": "build/src/bench_runnable/apply_rearrangment_int_1000/algo_apply_rearrangment_move",
    "num_cpus": 8,
    "mhz_per_cpu": 4900,
    "cpu_scaling_enabled": false,
    "caches": [
      {
        "type": "Data",
        "level": 1,
        "size": 32768,
        "num_sharing": 1
      },
      {
        "type": "Instruction",
        "level": 1,
        "size": 32768,
        "num_sharing": 1
      },
      {
        "type": "Unified",
        "level": 2,
        "size": 262144,
        "num_sharing": 1
      },
      {
        "type": "Unified",
        "level": 3,
        "size": 12582912,
        "num_sharing": 8
      }
    ],
    "load_avg": [0.17,0.54,0.78],
    "library_build_type": "release"
  },
  "benchmarks": [
    {
      "name": "apply_rearrangment_vec<SELECTED_ALGORITHM, SELECTED_TYPE>/1000/0",
      "run_name": "apply_rearrangment_vec<SELECTED_ALGORITHM, SELECTED_TYPE>/1000/0",
      "run_type": "iteration",
      "repetitions": 0,
      "repetition_index": 0,
      "threads": 1,
      "iterations": 1387781,
      "real_time": 4.9683345210753254e+02,
      "cpu_time": 4.9685194782173846e+02,
      "time_unit": "ns"
    },
    {
      "name": "apply_rearrangment_vec<SELECTED_ALGORITHM, SELECTED_TYPE>/1000/5",
      "run_name": "apply_rearrangment_vec<SELECTED_ALGORITHM, SELECTED_TYPE>/1000/5",
      "run_type": "iteration",
      "repetitions": 0,
      "repetition_index": 0,
      "threads": 1,
      "iterations": 1408024,
      "real_time": 4.9698165869364908e+02,
      "cpu_time": 4.9699964986392280e+02,
      "time_unit": "ns"
    },
    {
      "name": "apply_rearrangment_vec<SELECTED_ALGORITHM, SELECTED_TYPE>/1000/10",
      "run_name": "apply_rearrangment_vec<SELECTED_ALGORITHM, SELECTED_TYPE>/1000/10",
      "run_type": "iteration",
      "repetitions": 0,
      "repetition_index": 0,
      "threads": 1,
      "iterations": 1336683,
      "real_time": 5.1871397855629300e+02,
      "cpu_time": 5.1873298605578145e+02,
      "time_unit": "ns"
    },
    {
      "name": "apply_rearrangment_vec<SELECTED_ALGORITHM, SELECTED_TYPE>/1000/15",
      "run_name": "apply_rearrangment_vec<SELECTED_ALGORITHM, SELECTED_TYPE>/1000/15",
      "run_type": "iteration",
      "repetitions": 0,
      "repetition_index": 0,
      "threads": 1,
      "iterations": 1412499,
      "real_time": 4.9580485720792529e+02,
      "cpu_time": 4.9581678783489406e+02,
      "time_unit": "ns"
    },
    {
      "name": "apply_rearrangment_vec<SELECTED_ALGORITHM, SELECTED_TYPE>/1000/20",
      "run_name": "apply_rearrangment_vec<SELECTED_ALGORITHM, SELECTED_TYPE>/1000/20",
      "run_type": "iteration",
      "repetitions": 0,
      "repetition_index": 0,
      "threads": 1,
      "iterations": 1347120,
      "real_time": 5.1685603806710594e+02,
      "cpu_time": 5.1687400008907878e+02,
      "time_unit": "ns"
    },
    {
      "name": "apply_rearrangment_vec<SELECTED_ALGORITHM, SELECTED_TYPE>/1000/25",
      "run_name": "apply_rearrangment_vec<SELECTED_ALGORITHM, SELECTED_TYPE>/1000/25",
      "run_type": "iteration",
      "repetitions": 0,
      "repetition_index": 0,
      "threads": 1,
      "iterations": 1412920,
      "real_time": 4.9557736177587697e+02,
      "cpu_time": 4.9559637700648284e+02,
      "time_unit": "ns"
    },
    {
      "name": "apply_rearrangment_vec<SELECTED_ALGORITHM, SELECTED_TYPE>/1000/30",
      "run_name": "apply_rearrangment_vec<SELECTED_ALGORITHM, SELECTED_TYPE>/1000/30",
      "run_type": "iteration",
      "repetitions": 0,
      "repetition_index": 0,
      "threads": 1,
      "iterations": 1352383,
      "real_time": 5.1627321254345804e+02,
      "cpu_time": 5.1628953632218099e+02,
      "time_unit": "ns"
    },
    {
      "name": "apply_rearrangment_vec<SELECTED_ALGORITHM, SELECTED_TYPE>/1000/35",
      "run_name": "apply_rearrangment_vec<SELECTED_ALGORITHM, SELECTED_TYPE>/1000/35",
      "run_type": "iteration",
      "repetitions": 0,
      "repetition_index": 0,
      "threads": 1,
      "iterations": 1412143,
      "real_time": 4.9563148987136145e+02,
      "cpu_time": 4.9564818860412845e+02,
      "time_unit": "ns"
    },
    {
      "name": "apply_rearrangment_vec<SELECTED_ALGORITHM, SELECTED_TYPE>/1000/40",
      "run_name": "apply_rearrangment_vec<SELECTED_ALGORITHM, SELECTED_TYPE>/1000/40",
      "run_type": "iteration",
      "repetitions": 0,
      "repetition_index": 0,
      "threads": 1,
      "iterations": 1348018,
      "real_time": 5.1670198394935846e+02,
      "cpu_time": 5.1671852749740742e+02,
      "time_unit": "ns"
    },
    {
      "name": "apply_rearrangment_vec<SELECTED_ALGORITHM, SELECTED_TYPE>/1000/45",
      "run_name": "apply_rearrangment_vec<SELECTED_ALGORITHM, SELECTED_TYPE>/1000/45",
      "run_type": "iteration",
      "repetitions": 0,
      "repetition_index": 0,
      "threads": 1,
      "iterations": 1412548,
      "real_time": 4.9554060817641374e+02,
      "cpu_time": 4.9555906135579153e+02,
      "time_unit": "ns"
    },
    {
      "name": "apply_rearrangment_vec<SELECTED_ALGORITHM, SELECTED_TYPE>/1000/50",
      "run_name": "apply_rearrangment_vec<SELECTED_ALGORITHM, SELECTED_TYPE>/1000/50",
      "run_type": "iteration",
      "repetitions": 0,
      "repetition_index": 0,
      "threads": 1,
      "iterations": 1350168,
      "real_time": 5.1640047238603131e+02,
      "cpu_time": 5.1641830424065824e+02,
      "time_unit": "ns"
    },
    {
      "name": "apply_rearrangment_vec<SELECTED_ALGORITHM, SELECTED_TYPE>/1000/55",
      "run_name": "apply_rearrangment_vec<SELECTED_ALGORITHM, SELECTED_TYPE>/1000/55",
      "run_type": "iteration",
      "repetitions": 0,
      "repetition_index": 0,
      "threads": 1,
      "iterations": 1349843,
      "real_time": 5.1656889504896458e+02,
      "cpu_time": 5.1658587924669780e+02,
      "time_unit": "ns"
    },
    {
      "name": "apply_rearrangment_vec<SELECTED_ALGORITHM, SELECTED_TYPE>/1000/60",
      "run_name": "apply_rearrangment_vec<SELECTED_ALGORITHM, SELECTED_TYPE>/1000/60",
      "run_type": "iteration",
      "repetitions": 0,
      "repetition_index": 0,
      "threads": 1,
      "iterations": 1349711,
      "real_time": 5.1678082048669887e+02,
      "cpu_time": 5.1679879322314241e+02,
      "time_unit": "ns"
    },
    {
      "name": "apply_rearrangment_vec<SELECTED_ALGORITHM, SELECTED_TYPE>/1000/65",
      "run_name": "apply_rearrangment_vec<SELECTED_ALGORITHM, SELECTED_TYPE>/1000/65",
      "run_type": "iteration",
      "repetitions": 0,
      "repetition_index": 0,
      "threads": 1,
      "iterations": 1349289,
      "real_time": 5.1711182926640663e+02,
      "cpu_time": 5.1712804743831771e+02,
      "time_unit": "ns"
    },
    {
      "name": "apply_rearrangment_vec<SELECTED_ALGORITHM, SELECTED_TYPE>/1000/70",
      "run_name": "apply_rearrangment_vec<SELECTED_ALGORITHM, SELECTED_TYPE>/1000/70",
      "run_type": "iteration",
      "repetitions": 0,
      "repetition_index": 0,
      "threads": 1,
      "iterations": 1350633,
      "real_time": 5.1661342718629294e+02,
      "cpu_time": 5.1663279588163550e+02,
      "time_unit": "ns"
    },
    {
      "name": "apply_rearrangment_vec<SELECTED_ALGORITHM, SELECTED_TYPE>/1000/75",
      "run_name": "apply_rearrangment_vec<SELECTED_ALGORITHM, SELECTED_TYPE>/1000/75",
      "run_type": "iteration",
      "repetitions": 0,
      "repetition_index": 0,
      "threads": 1,
      "iterations": 1349655,
      "real_time": 5.1657867603085776e+02,
      "cpu_time": 5.1659509800652768e+02,
      "time_unit": "ns"
    },
    {
      "name": "apply_rearrangment_vec<SELECTED_ALGORITHM, SELECTED_TYPE>/1000/80",
      "run_name": "apply_rearrangment_vec<SELECTED_ALGORITHM, SELECTED_TYPE>/1000/80",
      "run_type": "iteration",
      "repetitions": 0,
      "repetition_index": 0,
      "threads": 1,
      "iterations": 1350251,
      "real_time": 5.1645924868740542e+02,
      "cpu_time": 5.1647967229796495e+02,
      "time_unit": "ns"
    },
    {
      "name": "apply_rearrangment_vec<SELECTED_ALGORITHM, SELECTED_TYPE>/1000/85",
      "run_name": "apply_rearrangment_vec<SELECTED_ALGORITHM, SELECTED_TYPE>/1000/85",
      "run_type": "iteration",
      "repetitions": 0,
      "repetition_index": 0,
      "threads": 1,
      "iterations": 1350390,
      "real_time": 5.1682744318323205e+02,
      "cpu_time": 5.1684608002132779e+02,
      "time_unit": "ns"
    },
    {
      "name": "apply_rearrangment_vec<SELECTED_ALGORITHM, SELECTED_TYPE>/1000/90",
      "run_name": "apply_rearrangment_vec<SELECTED_ALGORITHM, SELECTED_TYPE>/1000/90",
      "run_type": "iteration",
      "repetitions": 0,
      "repetition_index": 0,
      "threads": 1,
      "iterations": 1350641,
      "real_time": 5.1673083595125229e+02,
      "cpu_time": 5.1674892736115407e+02,
      "time_unit": "ns"
    },
    {
      "name": "apply_rearrangment_vec<SELECTED_ALGORITHM, SELECTED_TYPE>/1000/95",
      "run_name": "apply_rearrangment_vec<SELECTED_ALGORITHM, SELECTED_TYPE>/1000/95",
      "run_type": "iteration",
      "repetitions": 0,
      "repetition_index": 0,
      "threads": 1,
      "iterations": 1350541,
      "real_time": 5.1671328600974982e+02,
      "cpu_time": 5.1672881089874306e+02,
      "time_unit": "ns"
    },
    {
      "name": "apply_rearrangment_vec<SELECTED_ALGORITHM, SELECTED_TYPE>/1000/100",
      "run_name": "apply_rearrangment_vec<SELECTED_ALGORITHM, SELECTED_TYPE>/1000/100",
      "run_type": "iteration",
      "repetitions": 0,
      "repetition_index": 0,
      "threads": 1,
      "iterations": 1339229,
      "real_time": 5.1670423803542337e+02,
      "cpu_time": 5.1672082668460757e+02,
      "time_unit": "ns"
    }
  ]
}
