{
  "context": {
    "date": "2019-09-11 13:05:17",
    "executable": "build/src/bench_runnable/sort_fake_url_pair_1000/algo_stable_sort_sufficient_allocation",
    "num_cpus": 4,
    "mhz_per_cpu": 1800,
    "cpu_scaling_enabled": false,
    "caches": [
      {
        "type": "Data",
        "level": 1,
        "size": 32768000,
        "num_sharing": 2
      },
      {
        "type": "Instruction",
        "level": 1,
        "size": 32768000,
        "num_sharing": 2
      },
      {
        "type": "Unified",
        "level": 2,
        "size": 262144000,
        "num_sharing": 2
      },
      {
        "type": "Unified",
        "level": 3,
        "size": 3145728000,
        "num_sharing": 4
      }
    ],
    "library_build_type": "release"
  },
  "benchmarks": [
    {
      "name": "sort_vec<SELECTED_ALGORITHM, SELECTED_TYPE>/1000/0",
      "iterations": 4081,
      "real_time": 1.6962309458457588e+05,
      "cpu_time": 1.6932467532467534e+05,
      "time_unit": "ns"
    },
    {
      "name": "sort_vec<SELECTED_ALGORITHM, SELECTED_TYPE>/1000/5",
      "iterations": 2697,
      "real_time": 2.5865038042307436e+05,
      "cpu_time": 2.5810641453466823e+05,
      "time_unit": "ns"
    },
    {
      "name": "sort_vec<SELECTED_ALGORITHM, SELECTED_TYPE>/1000/10",
      "iterations": 2615,
      "real_time": 2.6652529789596738e+05,
      "cpu_time": 2.6607992351816432e+05,
      "time_unit": "ns"
    },
    {
      "name": "sort_vec<SELECTED_ALGORITHM, SELECTED_TYPE>/1000/15",
      "iterations": 2529,
      "real_time": 2.7590472044239281e+05,
      "cpu_time": 2.7542388295769069e+05,
      "time_unit": "ns"
    },
    {
      "name": "sort_vec<SELECTED_ALGORITHM, SELECTED_TYPE>/1000/20",
      "iterations": 2577,
      "real_time": 2.7041823166508559e+05,
      "cpu_time": 2.6994062863795098e+05,
      "time_unit": "ns"
    },
    {
      "name": "sort_vec<SELECTED_ALGORITHM, SELECTED_TYPE>/1000/25",
      "iterations": 2327,
      "real_time": 2.9099827073519467e+05,
      "cpu_time": 2.9038762354963471e+05,
      "time_unit": "ns"
    },
    {
      "name": "sort_vec<SELECTED_ALGORITHM, SELECTED_TYPE>/1000/30",
      "iterations": 2520,
      "real_time": 2.7640156269828568e+05,
      "cpu_time": 2.7575357142857125e+05,
      "time_unit": "ns"
    },
    {
      "name": "sort_vec<SELECTED_ALGORITHM, SELECTED_TYPE>/1000/35",
      "iterations": 2420,
      "real_time": 2.8854188553813112e+05,
      "cpu_time": 2.8804999999999953e+05,
      "time_unit": "ns"
    },
    {
      "name": "sort_vec<SELECTED_ALGORITHM, SELECTED_TYPE>/1000/40",
      "iterations": 2372,
      "real_time": 2.9449247976352135e+05,
      "cpu_time": 2.9393971332209086e+05,
      "time_unit": "ns"
    },
    {
      "name": "sort_vec<SELECTED_ALGORITHM, SELECTED_TYPE>/1000/45",
      "iterations": 2464,
      "real_time": 2.8265276988680521e+05,
      "cpu_time": 2.8215462662337639e+05,
      "time_unit": "ns"
    },
    {
      "name": "sort_vec<SELECTED_ALGORITHM, SELECTED_TYPE>/1000/50",
      "iterations": 2466,
      "real_time": 2.8394357380274055e+05,
      "cpu_time": 2.8335320356853178e+05,
      "time_unit": "ns"
    },
    {
      "name": "sort_vec<SELECTED_ALGORITHM, SELECTED_TYPE>/1000/55",
      "iterations": 2459,
      "real_time": 2.8347818910064921e+05,
      "cpu_time": 2.8287067913786107e+05,
      "time_unit": "ns"
    },
    {
      "name": "sort_vec<SELECTED_ALGORITHM, SELECTED_TYPE>/1000/60",
      "iterations": 2427,
      "real_time": 2.8843386856317474e+05,
      "cpu_time": 2.8792913061392703e+05,
      "time_unit": "ns"
    },
    {
      "name": "sort_vec<SELECTED_ALGORITHM, SELECTED_TYPE>/1000/65",
      "iterations": 2455,
      "real_time": 2.8415319837059337e+05,
      "cpu_time": 2.8367128309572220e+05,
      "time_unit": "ns"
    },
    {
      "name": "sort_vec<SELECTED_ALGORITHM, SELECTED_TYPE>/1000/70",
      "iterations": 2486,
      "real_time": 2.8330305189022631e+05,
      "cpu_time": 2.8277312952534237e+05,
      "time_unit": "ns"
    },
    {
      "name": "sort_vec<SELECTED_ALGORITHM, SELECTED_TYPE>/1000/75",
      "iterations": 2458,
      "real_time": 2.8360378234336048e+05,
      "cpu_time": 2.8306753458095976e+05,
      "time_unit": "ns"
    },
    {
      "name": "sort_vec<SELECTED_ALGORITHM, SELECTED_TYPE>/1000/80",
      "iterations": 2463,
      "real_time": 2.8349618473409466e+05,
      "cpu_time": 2.8293950466910278e+05,
      "time_unit": "ns"
    },
    {
      "name": "sort_vec<SELECTED_ALGORITHM, SELECTED_TYPE>/1000/85",
      "iterations": 2610,
      "real_time": 2.6724553486559552e+05,
      "cpu_time": 2.6678888888888987e+05,
      "time_unit": "ns"
    },
    {
      "name": "sort_vec<SELECTED_ALGORITHM, SELECTED_TYPE>/1000/90",
      "iterations": 2602,
      "real_time": 2.6824551960096584e+05,
      "cpu_time": 2.6776863950807182e+05,
      "time_unit": "ns"
    },
    {
      "name": "sort_vec<SELECTED_ALGORITHM, SELECTED_TYPE>/1000/95",
      "iterations": 2707,
      "real_time": 2.5820423568521778e+05,
      "cpu_time": 2.5771739933505756e+05,
      "time_unit": "ns"
    },
    {
      "name": "sort_vec<SELECTED_ALGORITHM, SELECTED_TYPE>/1000/100",
      "iterations": 3722,
      "real_time": 1.8697375094026601e+05,
      "cpu_time": 1.8663433637829093e+05,
      "time_unit": "ns"
    }
  ]
}
