{
  "context": {
    "date": "2019-09-11 16:22:43",
    "executable": "build/src/bench_runnable/sort_int_1000/algo_stable_sort_lifting",
    "num_cpus": 4,
    "mhz_per_cpu": 1800,
    "cpu_scaling_enabled": false,
    "caches": [
      {
        "type": "Data",
        "level": 1,
        "size": 32768000,
        "num_sharing": 2
      },
      {
        "type": "Instruction",
        "level": 1,
        "size": 32768000,
        "num_sharing": 2
      },
      {
        "type": "Unified",
        "level": 2,
        "size": 262144000,
        "num_sharing": 2
      },
      {
        "type": "Unified",
        "level": 3,
        "size": 3145728000,
        "num_sharing": 4
      }
    ],
    "library_build_type": "release"
  },
  "benchmarks": [
    {
      "name": "sort_vec<SELECTED_ALGORITHM, SELECTED_TYPE>/1000/0",
      "iterations": 83720,
      "real_time": 8.2483312111847172e+03,
      "cpu_time": 8.2308647873865248e+03,
      "time_unit": "ns"
    },
    {
      "name": "sort_vec<SELECTED_ALGORITHM, SELECTED_TYPE>/1000/5",
      "iterations": 30728,
      "real_time": 2.2862200045568992e+04,
      "cpu_time": 2.2818439208539443e+04,
      "time_unit": "ns"
    },
    {
      "name": "sort_vec<SELECTED_ALGORITHM, SELECTED_TYPE>/1000/10",
      "iterations": 23617,
      "real_time": 3.1187406275218047e+04,
      "cpu_time": 3.1132997417114791e+04,
      "time_unit": "ns"
    },
    {
      "name": "sort_vec<SELECTED_ALGORITHM, SELECTED_TYPE>/1000/15",
      "iterations": 23364,
      "real_time": 2.9904106702510748e+04,
      "cpu_time": 2.9842492723848653e+04,
      "time_unit": "ns"
    },
    {
      "name": "sort_vec<SELECTED_ALGORITHM, SELECTED_TYPE>/1000/20",
      "iterations": 22005,
      "real_time": 3.1693303249117180e+04,
      "cpu_time": 3.1623630992956125e+04,
      "time_unit": "ns"
    },
    {
      "name": "sort_vec<SELECTED_ALGORITHM, SELECTED_TYPE>/1000/25",
      "iterations": 21442,
      "real_time": 3.2618648819988975e+04,
      "cpu_time": 3.2559182912041808e+04,
      "time_unit": "ns"
    },
    {
      "name": "sort_vec<SELECTED_ALGORITHM, SELECTED_TYPE>/1000/30",
      "iterations": 20277,
      "real_time": 3.4709865660481628e+04,
      "cpu_time": 3.4599891502687780e+04,
      "time_unit": "ns"
    },
    {
      "name": "sort_vec<SELECTED_ALGORITHM, SELECTED_TYPE>/1000/35",
      "iterations": 20121,
      "real_time": 3.4742311117724072e+04,
      "cpu_time": 3.4681079469211349e+04,
      "time_unit": "ns"
    },
    {
      "name": "sort_vec<SELECTED_ALGORITHM, SELECTED_TYPE>/1000/40",
      "iterations": 19994,
      "real_time": 3.4896233920051789e+04,
      "cpu_time": 3.4840902270681137e+04,
      "time_unit": "ns"
    },
    {
      "name": "sort_vec<SELECTED_ALGORITHM, SELECTED_TYPE>/1000/45",
      "iterations": 19589,
      "real_time": 3.6179644085927233e+04,
      "cpu_time": 3.6094287610393585e+04,
      "time_unit": "ns"
    },
    {
      "name": "sort_vec<SELECTED_ALGORITHM, SELECTED_TYPE>/1000/50",
      "iterations": 19571,
      "real_time": 3.5631197945912761e+04,
      "cpu_time": 3.5556742118440641e+04,
      "time_unit": "ns"
    },
    {
      "name": "sort_vec<SELECTED_ALGORITHM, SELECTED_TYPE>/1000/55",
      "iterations": 19734,
      "real_time": 3.5341045099934752e+04,
      "cpu_time": 3.5270750988142194e+04,
      "time_unit": "ns"
    },
    {
      "name": "sort_vec<SELECTED_ALGORITHM, SELECTED_TYPE>/1000/60",
      "iterations": 20005,
      "real_time": 3.5059870882354640e+04,
      "cpu_time": 3.4991002249437530e+04,
      "time_unit": "ns"
    },
    {
      "name": "sort_vec<SELECTED_ALGORITHM, SELECTED_TYPE>/1000/65",
      "iterations": 19956,
      "real_time": 3.5063028763239803e+04,
      "cpu_time": 3.4981559430747686e+04,
      "time_unit": "ns"
    },
    {
      "name": "sort_vec<SELECTED_ALGORITHM, SELECTED_TYPE>/1000/70",
      "iterations": 20695,
      "real_time": 3.3596936554762062e+04,
      "cpu_time": 3.3540227107997191e+04,
      "time_unit": "ns"
    },
    {
      "name": "sort_vec<SELECTED_ALGORITHM, SELECTED_TYPE>/1000/75",
      "iterations": 21137,
      "real_time": 3.3095812840023355e+04,
      "cpu_time": 3.3031366797558680e+04,
      "time_unit": "ns"
    },
    {
      "name": "sort_vec<SELECTED_ALGORITHM, SELECTED_TYPE>/1000/80",
      "iterations": 22467,
      "real_time": 3.1030219522041225e+04,
      "cpu_time": 3.0979302977700452e+04,
      "time_unit": "ns"
    },
    {
      "name": "sort_vec<SELECTED_ALGORITHM, SELECTED_TYPE>/1000/85",
      "iterations": 23642,
      "real_time": 2.9245103544560883e+04,
      "cpu_time": 2.9192919380763073e+04,
      "time_unit": "ns"
    },
    {
      "name": "sort_vec<SELECTED_ALGORITHM, SELECTED_TYPE>/1000/90",
      "iterations": 25739,
      "real_time": 2.7202527137784531e+04,
      "cpu_time": 2.7142118963440680e+04,
      "time_unit": "ns"
    },
    {
      "name": "sort_vec<SELECTED_ALGORITHM, SELECTED_TYPE>/1000/95",
      "iterations": 31319,
      "real_time": 2.2204562438106630e+04,
      "cpu_time": 2.2168236533733489e+04,
      "time_unit": "ns"
    },
    {
      "name": "sort_vec<SELECTED_ALGORITHM, SELECTED_TYPE>/1000/100",
      "iterations": 56176,
      "real_time": 1.2200583327395483e+04,
      "cpu_time": 1.2179898889205379e+04,
      "time_unit": "ns"
    }
  ]
}
