{
  "context": {
    "date": "2019-08-28 21:12:20",
    "executable": "build/src/bench_runnable/lower_bound_first_5_percent_int_1000/algo_lower_bound_linear",
    "num_cpus": 4,
    "mhz_per_cpu": 1800,
    "cpu_scaling_enabled": false,
    "caches": [
      {
        "type": "Data",
        "level": 1,
        "size": 32768000,
        "num_sharing": 2
      },
      {
        "type": "Instruction",
        "level": 1,
        "size": 32768000,
        "num_sharing": 2
      },
      {
        "type": "Unified",
        "level": 2,
        "size": 262144000,
        "num_sharing": 2
      },
      {
        "type": "Unified",
        "level": 3,
        "size": 3145728000,
        "num_sharing": 4
      }
    ],
    "library_build_type": "release"
  },
  "benchmarks": [
    {
      "name": "lower_bound_vec_first_5_percent<SELECTED_ALGORITHM, SELECTED_TYPE>/1000/0",
      "iterations": 969139819,
      "real_time": 6.9559045432216260e-01,
      "cpu_time": 6.9480789747634952e-01,
      "time_unit": "ns"
    },
    {
      "name": "lower_bound_vec_first_5_percent<SELECTED_ALGORITHM, SELECTED_TYPE>/1000/2",
      "iterations": 992555831,
      "real_time": 6.9738900360454470e-01,
      "cpu_time": 6.9634773018627305e-01,
      "time_unit": "ns"
    },
    {
      "name": "lower_bound_vec_first_5_percent<SELECTED_ALGORITHM, SELECTED_TYPE>/1000/4",
      "iterations": 426766815,
      "real_time": 1.7129197873536359e+00,
      "cpu_time": 1.7097369672475586e+00,
      "time_unit": "ns"
    },
    {
      "name": "lower_bound_vec_first_5_percent<SELECTED_ALGORITHM, SELECTED_TYPE>/1000/6",
      "iterations": 299593409,
      "real_time": 2.3206472843360100e+00,
      "cpu_time": 2.3172806181460421e+00,
      "time_unit": "ns"
    },
    {
      "name": "lower_bound_vec_first_5_percent<SELECTED_ALGORITHM, SELECTED_TYPE>/1000/8",
      "iterations": 209085044,
      "real_time": 3.5584340982286844e+00,
      "cpu_time": 3.5519087630198953e+00,
      "time_unit": "ns"
    },
    {
      "name": "lower_bound_vec_first_5_percent<SELECTED_ALGORITHM, SELECTED_TYPE>/1000/10",
      "iterations": 174788942,
      "real_time": 4.1345999680027026e+00,
      "cpu_time": 4.1270402563567199e+00,
      "time_unit": "ns"
    },
    {
      "name": "lower_bound_vec_first_5_percent<SELECTED_ALGORITHM, SELECTED_TYPE>/1000/12",
      "iterations": 209136267,
      "real_time": 3.3544937904014556e+00,
      "cpu_time": 3.3492995263227132e+00,
      "time_unit": "ns"
    },
    {
      "name": "lower_bound_vec_first_5_percent<SELECTED_ALGORITHM, SELECTED_TYPE>/1000/14",
      "iterations": 184078281,
      "real_time": 3.8312721640495755e+00,
      "cpu_time": 3.8238623056242003e+00,
      "time_unit": "ns"
    },
    {
      "name": "lower_bound_vec_first_5_percent<SELECTED_ALGORITHM, SELECTED_TYPE>/1000/16",
      "iterations": 172881339,
      "real_time": 4.1295733775042569e+00,
      "cpu_time": 4.1231749136325169e+00,
      "time_unit": "ns"
    },
    {
      "name": "lower_bound_vec_first_5_percent<SELECTED_ALGORITHM, SELECTED_TYPE>/1000/18",
      "iterations": 146507573,
      "real_time": 4.8217527089864456e+00,
      "cpu_time": 4.8128638374208830e+00,
      "time_unit": "ns"
    },
    {
      "name": "lower_bound_vec_first_5_percent<SELECTED_ALGORITHM, SELECTED_TYPE>/1000/20",
      "iterations": 130472871,
      "real_time": 5.0159866950449370e+00,
      "cpu_time": 5.0081828888397837e+00,
      "time_unit": "ns"
    },
    {
      "name": "lower_bound_vec_first_5_percent<SELECTED_ALGORITHM, SELECTED_TYPE>/1000/22",
      "iterations": 122283558,
      "real_time": 5.4819133902032107e+00,
      "cpu_time": 5.4731560885724386e+00,
      "time_unit": "ns"
    },
    {
      "name": "lower_bound_vec_first_5_percent<SELECTED_ALGORITHM, SELECTED_TYPE>/1000/24",
      "iterations": 122061798,
      "real_time": 5.7400604077741280e+00,
      "cpu_time": 5.7302940925054928e+00,
      "time_unit": "ns"
    },
    {
      "name": "lower_bound_vec_first_5_percent<SELECTED_ALGORITHM, SELECTED_TYPE>/1000/26",
      "iterations": 112213655,
      "real_time": 6.0595559159222443e+00,
      "cpu_time": 6.0484973954372938e+00,
      "time_unit": "ns"
    },
    {
      "name": "lower_bound_vec_first_5_percent<SELECTED_ALGORITHM, SELECTED_TYPE>/1000/28",
      "iterations": 106805005,
      "real_time": 6.6699215266029670e+00,
      "cpu_time": 6.6592946650767999e+00,
      "time_unit": "ns"
    },
    {
      "name": "lower_bound_vec_first_5_percent<SELECTED_ALGORITHM, SELECTED_TYPE>/1000/30",
      "iterations": 98900788,
      "real_time": 6.9360477390450628e+00,
      "cpu_time": 6.9239589880719636e+00,
      "time_unit": "ns"
    },
    {
      "name": "lower_bound_vec_first_5_percent<SELECTED_ALGORITHM, SELECTED_TYPE>/1000/32",
      "iterations": 93984962,
      "real_time": 7.4593591260151300e+00,
      "cpu_time": 7.4474786721730943e+00,
      "time_unit": "ns"
    },
    {
      "name": "lower_bound_vec_first_5_percent<SELECTED_ALGORITHM, SELECTED_TYPE>/1000/34",
      "iterations": 90839487,
      "real_time": 7.7936552856164729e+00,
      "cpu_time": 7.7782473606439204e+00,
      "time_unit": "ns"
    },
    {
      "name": "lower_bound_vec_first_5_percent<SELECTED_ALGORITHM, SELECTED_TYPE>/1000/36",
      "iterations": 86619727,
      "real_time": 8.1499111743961219e+00,
      "cpu_time": 8.1365299154083015e+00,
      "time_unit": "ns"
    },
    {
      "name": "lower_bound_vec_first_5_percent<SELECTED_ALGORITHM, SELECTED_TYPE>/1000/38",
      "iterations": 83369063,
      "real_time": 8.3326706574630087e+00,
      "cpu_time": 8.3191531131878200e+00,
      "time_unit": "ns"
    },
    {
      "name": "lower_bound_vec_first_5_percent<SELECTED_ALGORITHM, SELECTED_TYPE>/1000/40",
      "iterations": 80671184,
      "real_time": 8.4854636693960028e+00,
      "cpu_time": 8.4707198545641855e+00,
      "time_unit": "ns"
    },
    {
      "name": "lower_bound_vec_first_5_percent<SELECTED_ALGORITHM, SELECTED_TYPE>/1000/42",
      "iterations": 77885086,
      "real_time": 8.7835285435789761e+00,
      "cpu_time": 8.7726166213644561e+00,
      "time_unit": "ns"
    },
    {
      "name": "lower_bound_vec_first_5_percent<SELECTED_ALGORITHM, SELECTED_TYPE>/1000/44",
      "iterations": 75901328,
      "real_time": 9.2371356532719044e+00,
      "cpu_time": 9.2189954831883760e+00,
      "time_unit": "ns"
    },
    {
      "name": "lower_bound_vec_first_5_percent<SELECTED_ALGORITHM, SELECTED_TYPE>/1000/46",
      "iterations": 75584158,
      "real_time": 9.3168287063123767e+00,
      "cpu_time": 9.2989459510814569e+00,
      "time_unit": "ns"
    },
    {
      "name": "lower_bound_vec_first_5_percent<SELECTED_ALGORITHM, SELECTED_TYPE>/1000/48",
      "iterations": 68907133,
      "real_time": 9.9719458652076582e+00,
      "cpu_time": 9.9581417790230340e+00,
      "time_unit": "ns"
    },
    {
      "name": "lower_bound_vec_first_5_percent<SELECTED_ALGORITHM, SELECTED_TYPE>/1000/50",
      "iterations": 68036468,
      "real_time": 1.0332917943316032e+01,
      "cpu_time": 1.0314865257261731e+01,
      "time_unit": "ns"
    },
    {
      "name": "lower_bound_vec_first_5_percent<SELECTED_ALGORITHM, SELECTED_TYPE>/1000/52",
      "iterations": 65817929,
      "real_time": 1.0611849288056666e+01,
      "cpu_time": 1.0594560032419132e+01,
      "time_unit": "ns"
    },
    {
      "name": "lower_bound_vec_first_5_percent<SELECTED_ALGORITHM, SELECTED_TYPE>/1000/54",
      "iterations": 62268162,
      "real_time": 1.1158833996105416e+01,
      "cpu_time": 1.1137601909624333e+01,
      "time_unit": "ns"
    },
    {
      "name": "lower_bound_vec_first_5_percent<SELECTED_ALGORITHM, SELECTED_TYPE>/1000/56",
      "iterations": 60414095,
      "real_time": 1.1366495600058146e+01,
      "cpu_time": 1.1342551767100042e+01,
      "time_unit": "ns"
    },
    {
      "name": "lower_bound_vec_first_5_percent<SELECTED_ALGORITHM, SELECTED_TYPE>/1000/58",
      "iterations": 57262993,
      "real_time": 1.2017507170793129e+01,
      "cpu_time": 1.1996211933944885e+01,
      "time_unit": "ns"
    },
    {
      "name": "lower_bound_vec_first_5_percent<SELECTED_ALGORITHM, SELECTED_TYPE>/1000/60",
      "iterations": 56164900,
      "real_time": 1.2497767182014520e+01,
      "cpu_time": 1.2479359884910314e+01,
      "time_unit": "ns"
    },
    {
      "name": "lower_bound_vec_first_5_percent<SELECTED_ALGORITHM, SELECTED_TYPE>/1000/62",
      "iterations": 54154836,
      "real_time": 1.2763212725806619e+01,
      "cpu_time": 1.2743054009063982e+01,
      "time_unit": "ns"
    },
    {
      "name": "lower_bound_vec_first_5_percent<SELECTED_ALGORITHM, SELECTED_TYPE>/1000/64",
      "iterations": 53623410,
      "real_time": 1.2997493911675379e+01,
      "cpu_time": 1.2978883662937534e+01,
      "time_unit": "ns"
    },
    {
      "name": "lower_bound_vec_first_5_percent<SELECTED_ALGORITHM, SELECTED_TYPE>/1000/66",
      "iterations": 50483196,
      "real_time": 1.3466717440044553e+01,
      "cpu_time": 1.3445741430475278e+01,
      "time_unit": "ns"
    },
    {
      "name": "lower_bound_vec_first_5_percent<SELECTED_ALGORITHM, SELECTED_TYPE>/1000/68",
      "iterations": 25062746,
      "real_time": 2.7713651608588219e+01,
      "cpu_time": 2.7662770871156827e+01,
      "time_unit": "ns"
    },
    {
      "name": "lower_bound_vec_first_5_percent<SELECTED_ALGORITHM, SELECTED_TYPE>/1000/70",
      "iterations": 25191274,
      "real_time": 2.7852851149942726e+01,
      "cpu_time": 2.7808915102904230e+01,
      "time_unit": "ns"
    },
    {
      "name": "lower_bound_vec_first_5_percent<SELECTED_ALGORITHM, SELECTED_TYPE>/1000/72",
      "iterations": 47303690,
      "real_time": 1.4735935040206142e+01,
      "cpu_time": 1.4714919702881431e+01,
      "time_unit": "ns"
    },
    {
      "name": "lower_bound_vec_first_5_percent<SELECTED_ALGORITHM, SELECTED_TYPE>/1000/74",
      "iterations": 45928443,
      "real_time": 1.5428421816925560e+01,
      "cpu_time": 1.5404963760691853e+01,
      "time_unit": "ns"
    },
    {
      "name": "lower_bound_vec_first_5_percent<SELECTED_ALGORITHM, SELECTED_TYPE>/1000/76",
      "iterations": 32949239,
      "real_time": 1.8786056303149802e+01,
      "cpu_time": 1.8760402933736994e+01,
      "time_unit": "ns"
    },
    {
      "name": "lower_bound_vec_first_5_percent<SELECTED_ALGORITHM, SELECTED_TYPE>/1000/78",
      "iterations": 25991386,
      "real_time": 2.7201785583887723e+01,
      "cpu_time": 2.7156227836406906e+01,
      "time_unit": "ns"
    },
    {
      "name": "lower_bound_vec_first_5_percent<SELECTED_ALGORITHM, SELECTED_TYPE>/1000/80",
      "iterations": 35147267,
      "real_time": 1.9028311532731642e+01,
      "cpu_time": 1.8995644810733086e+01,
      "time_unit": "ns"
    },
    {
      "name": "lower_bound_vec_first_5_percent<SELECTED_ALGORITHM, SELECTED_TYPE>/1000/82",
      "iterations": 35595694,
      "real_time": 1.8986842622068824e+01,
      "cpu_time": 1.8954483651870909e+01,
      "time_unit": "ns"
    },
    {
      "name": "lower_bound_vec_first_5_percent<SELECTED_ALGORITHM, SELECTED_TYPE>/1000/84",
      "iterations": 25842941,
      "real_time": 2.7252342525637069e+01,
      "cpu_time": 2.7200658005603920e+01,
      "time_unit": "ns"
    },
    {
      "name": "lower_bound_vec_first_5_percent<SELECTED_ALGORITHM, SELECTED_TYPE>/1000/86",
      "iterations": 23869522,
      "real_time": 2.8401562419272910e+01,
      "cpu_time": 2.8364623304983166e+01,
      "time_unit": "ns"
    },
    {
      "name": "lower_bound_vec_first_5_percent<SELECTED_ALGORITHM, SELECTED_TYPE>/1000/88",
      "iterations": 35929496,
      "real_time": 2.3674243273600410e+01,
      "cpu_time": 2.3639574571265968e+01,
      "time_unit": "ns"
    },
    {
      "name": "lower_bound_vec_first_5_percent<SELECTED_ALGORITHM, SELECTED_TYPE>/1000/90",
      "iterations": 32015221,
      "real_time": 2.4599598203530118e+01,
      "cpu_time": 2.4554976521948941e+01,
      "time_unit": "ns"
    },
    {
      "name": "lower_bound_vec_first_5_percent<SELECTED_ALGORITHM, SELECTED_TYPE>/1000/92",
      "iterations": 25930248,
      "real_time": 2.6972820236879919e+01,
      "cpu_time": 2.6932330149715341e+01,
      "time_unit": "ns"
    },
    {
      "name": "lower_bound_vec_first_5_percent<SELECTED_ALGORITHM, SELECTED_TYPE>/1000/94",
      "iterations": 23782667,
      "real_time": 2.8754369011682655e+01,
      "cpu_time": 2.8716964333730669e+01,
      "time_unit": "ns"
    },
    {
      "name": "lower_bound_vec_first_5_percent<SELECTED_ALGORITHM, SELECTED_TYPE>/1000/96",
      "iterations": 22977262,
      "real_time": 3.0619916289259919e+01,
      "cpu_time": 3.0568568178401456e+01,
      "time_unit": "ns"
    },
    {
      "name": "lower_bound_vec_first_5_percent<SELECTED_ALGORITHM, SELECTED_TYPE>/1000/98",
      "iterations": 23207164,
      "real_time": 3.0658495669692080e+01,
      "cpu_time": 3.0617226646047623e+01,
      "time_unit": "ns"
    },
    {
      "name": "lower_bound_vec_first_5_percent<SELECTED_ALGORITHM, SELECTED_TYPE>/1000/100",
      "iterations": 22255146,
      "real_time": 3.1327198392590478e+01,
      "cpu_time": 3.1282113359310220e+01,
      "time_unit": "ns"
    }
  ]
}
