{
  "context": {
    "date": "2020-03-07 23:59:04",
    "host_name": "m-desktop",
    "executable": "build/src/bench_runnable/merge_int_2000/algo_merge_expensive_cmp",
    "num_cpus": 12,
    "mhz_per_cpu": 3800,
    "cpu_scaling_enabled": false,
    "caches": [
      {
        "type": "Data",
        "level": 1,
        "size": 32768,
        "num_sharing": 2
      },
      {
        "type": "Instruction",
        "level": 1,
        "size": 32768,
        "num_sharing": 2
      },
      {
        "type": "Unified",
        "level": 2,
        "size": 524288,
        "num_sharing": 2
      },
      {
        "type": "Unified",
        "level": 3,
        "size": 16777216,
        "num_sharing": 6
      }
    ],
    "load_avg": [1.08,0.82,0.52],
    "library_build_type": "release"
  },
  "benchmarks": [
    {
      "name": "merge_vec<SELECTED_ALGORITHM, SELECTED_TYPE>/2000/0",
      "run_name": "merge_vec<SELECTED_ALGORITHM, SELECTED_TYPE>/2000/0",
      "run_type": "iteration",
      "repetitions": 0,
      "repetition_index": 0,
      "threads": 1,
      "iterations": 11380010,
      "real_time": 6.1380702653156057e+01,
      "cpu_time": 6.1380652389584903e+01,
      "time_unit": "ns"
    },
    {
      "name": "merge_vec<SELECTED_ALGORITHM, SELECTED_TYPE>/2000/1",
      "run_name": "merge_vec<SELECTED_ALGORITHM, SELECTED_TYPE>/2000/1",
      "run_type": "iteration",
      "repetitions": 0,
      "repetition_index": 0,
      "threads": 1,
      "iterations": 763596,
      "real_time": 9.1067481626434494e+02,
      "cpu_time": 9.1067907113185493e+02,
      "time_unit": "ns"
    },
    {
      "name": "merge_vec<SELECTED_ALGORITHM, SELECTED_TYPE>/2000/2",
      "run_name": "merge_vec<SELECTED_ALGORITHM, SELECTED_TYPE>/2000/2",
      "run_type": "iteration",
      "repetitions": 0,
      "repetition_index": 0,
      "threads": 1,
      "iterations": 742140,
      "real_time": 9.3779221171183281e+02,
      "cpu_time": 9.3779272913466480e+02,
      "time_unit": "ns"
    },
    {
      "name": "merge_vec<SELECTED_ALGORITHM, SELECTED_TYPE>/2000/3",
      "run_name": "merge_vec<SELECTED_ALGORITHM, SELECTED_TYPE>/2000/3",
      "run_type": "iteration",
      "repetitions": 0,
      "repetition_index": 0,
      "threads": 1,
      "iterations": 690191,
      "real_time": 1.0140272446320818e+03,
      "cpu_time": 1.0140151334920332e+03,
      "time_unit": "ns"
    },
    {
      "name": "merge_vec<SELECTED_ALGORITHM, SELECTED_TYPE>/2000/4",
      "run_name": "merge_vec<SELECTED_ALGORITHM, SELECTED_TYPE>/2000/4",
      "run_type": "iteration",
      "repetitions": 0,
      "repetition_index": 0,
      "threads": 1,
      "iterations": 695678,
      "real_time": 1.0115937660812970e+03,
      "cpu_time": 1.0115865673486870e+03,
      "time_unit": "ns"
    },
    {
      "name": "merge_vec<SELECTED_ALGORITHM, SELECTED_TYPE>/2000/5",
      "run_name": "merge_vec<SELECTED_ALGORITHM, SELECTED_TYPE>/2000/5",
      "run_type": "iteration",
      "repetitions": 0,
      "repetition_index": 0,
      "threads": 1,
      "iterations": 678350,
      "real_time": 1.0270316975011960e+03,
      "cpu_time": 1.0270301555244341e+03,
      "time_unit": "ns"
    },
    {
      "name": "merge_vec<SELECTED_ALGORITHM, SELECTED_TYPE>/2000/6",
      "run_name": "merge_vec<SELECTED_ALGORITHM, SELECTED_TYPE>/2000/6",
      "run_type": "iteration",
      "repetitions": 0,
      "repetition_index": 0,
      "threads": 1,
      "iterations": 859295,
      "real_time": 8.1873776642504356e+02,
      "cpu_time": 8.1873349664550608e+02,
      "time_unit": "ns"
    },
    {
      "name": "merge_vec<SELECTED_ALGORITHM, SELECTED_TYPE>/2000/7",
      "run_name": "merge_vec<SELECTED_ALGORITHM, SELECTED_TYPE>/2000/7",
      "run_type": "iteration",
      "repetitions": 0,
      "repetition_index": 0,
      "threads": 1,
      "iterations": 883336,
      "real_time": 7.9298384533183685e+02,
      "cpu_time": 7.9297711063513748e+02,
      "time_unit": "ns"
    },
    {
      "name": "merge_vec<SELECTED_ALGORITHM, SELECTED_TYPE>/2000/8",
      "run_name": "merge_vec<SELECTED_ALGORITHM, SELECTED_TYPE>/2000/8",
      "run_type": "iteration",
      "repetitions": 0,
      "repetition_index": 0,
      "threads": 1,
      "iterations": 880921,
      "real_time": 7.8976508790217747e+02,
      "cpu_time": 7.8975695436934836e+02,
      "time_unit": "ns"
    },
    {
      "name": "merge_vec<SELECTED_ALGORITHM, SELECTED_TYPE>/2000/9",
      "run_name": "merge_vec<SELECTED_ALGORITHM, SELECTED_TYPE>/2000/9",
      "run_type": "iteration",
      "repetitions": 0,
      "repetition_index": 0,
      "threads": 1,
      "iterations": 870028,
      "real_time": 7.8864624241965339e+02,
      "cpu_time": 7.8864644701090117e+02,
      "time_unit": "ns"
    },
    {
      "name": "merge_vec<SELECTED_ALGORITHM, SELECTED_TYPE>/2000/10",
      "run_name": "merge_vec<SELECTED_ALGORITHM, SELECTED_TYPE>/2000/10",
      "run_type": "iteration",
      "repetitions": 0,
      "repetition_index": 0,
      "threads": 1,
      "iterations": 853332,
      "real_time": 8.1188846779473897e+02,
      "cpu_time": 8.1188023418786520e+02,
      "time_unit": "ns"
    },
    {
      "name": "merge_vec<SELECTED_ALGORITHM, SELECTED_TYPE>/2000/11",
      "run_name": "merge_vec<SELECTED_ALGORITHM, SELECTED_TYPE>/2000/11",
      "run_type": "iteration",
      "repetitions": 0,
      "repetition_index": 0,
      "threads": 1,
      "iterations": 859959,
      "real_time": 8.2211794864618003e+02,
      "cpu_time": 8.2211167276579567e+02,
      "time_unit": "ns"
    },
    {
      "name": "merge_vec<SELECTED_ALGORITHM, SELECTED_TYPE>/2000/12",
      "run_name": "merge_vec<SELECTED_ALGORITHM, SELECTED_TYPE>/2000/12",
      "run_type": "iteration",
      "repetitions": 0,
      "repetition_index": 0,
      "threads": 1,
      "iterations": 869586,
      "real_time": 8.1575153578851712e+02,
      "cpu_time": 8.1574095374120418e+02,
      "time_unit": "ns"
    },
    {
      "name": "merge_vec<SELECTED_ALGORITHM, SELECTED_TYPE>/2000/13",
      "run_name": "merge_vec<SELECTED_ALGORITHM, SELECTED_TYPE>/2000/13",
      "run_type": "iteration",
      "repetitions": 0,
      "repetition_index": 0,
      "threads": 1,
      "iterations": 842057,
      "real_time": 8.1657181877240259e+02,
      "cpu_time": 8.1656303670653949e+02,
      "time_unit": "ns"
    },
    {
      "name": "merge_vec<SELECTED_ALGORITHM, SELECTED_TYPE>/2000/14",
      "run_name": "merge_vec<SELECTED_ALGORITHM, SELECTED_TYPE>/2000/14",
      "run_type": "iteration",
      "repetitions": 0,
      "repetition_index": 0,
      "threads": 1,
      "iterations": 810878,
      "real_time": 8.7965877357630370e+02,
      "cpu_time": 8.7965472611169719e+02,
      "time_unit": "ns"
    },
    {
      "name": "merge_vec<SELECTED_ALGORITHM, SELECTED_TYPE>/2000/15",
      "run_name": "merge_vec<SELECTED_ALGORITHM, SELECTED_TYPE>/2000/15",
      "run_type": "iteration",
      "repetitions": 0,
      "repetition_index": 0,
      "threads": 1,
      "iterations": 772168,
      "real_time": 8.7879407331056018e+02,
      "cpu_time": 8.7879023347250984e+02,
      "time_unit": "ns"
    },
    {
      "name": "merge_vec<SELECTED_ALGORITHM, SELECTED_TYPE>/2000/16",
      "run_name": "merge_vec<SELECTED_ALGORITHM, SELECTED_TYPE>/2000/16",
      "run_type": "iteration",
      "repetitions": 0,
      "repetition_index": 0,
      "threads": 1,
      "iterations": 767437,
      "real_time": 9.1024007964177156e+02,
      "cpu_time": 9.1022951460510785e+02,
      "time_unit": "ns"
    },
    {
      "name": "merge_vec<SELECTED_ALGORITHM, SELECTED_TYPE>/2000/17",
      "run_name": "merge_vec<SELECTED_ALGORITHM, SELECTED_TYPE>/2000/17",
      "run_type": "iteration",
      "repetitions": 0,
      "repetition_index": 0,
      "threads": 1,
      "iterations": 716446,
      "real_time": 9.8078083484308502e+02,
      "cpu_time": 9.8076608565055983e+02,
      "time_unit": "ns"
    },
    {
      "name": "merge_vec<SELECTED_ALGORITHM, SELECTED_TYPE>/2000/18",
      "run_name": "merge_vec<SELECTED_ALGORITHM, SELECTED_TYPE>/2000/18",
      "run_type": "iteration",
      "repetitions": 0,
      "repetition_index": 0,
      "threads": 1,
      "iterations": 714485,
      "real_time": 9.8354567275717545e+02,
      "cpu_time": 9.8352368349230517e+02,
      "time_unit": "ns"
    },
    {
      "name": "merge_vec<SELECTED_ALGORITHM, SELECTED_TYPE>/2000/19",
      "run_name": "merge_vec<SELECTED_ALGORITHM, SELECTED_TYPE>/2000/19",
      "run_type": "iteration",
      "repetitions": 0,
      "repetition_index": 0,
      "threads": 1,
      "iterations": 694610,
      "real_time": 9.8553281121801729e+02,
      "cpu_time": 9.8553422784008433e+02,
      "time_unit": "ns"
    },
    {
      "name": "merge_vec<SELECTED_ALGORITHM, SELECTED_TYPE>/2000/20",
      "run_name": "merge_vec<SELECTED_ALGORITHM, SELECTED_TYPE>/2000/20",
      "run_type": "iteration",
      "repetitions": 0,
      "repetition_index": 0,
      "threads": 1,
      "iterations": 697729,
      "real_time": 9.7519535091705075e+02,
      "cpu_time": 9.7518850155289283e+02,
      "time_unit": "ns"
    },
    {
      "name": "merge_vec<SELECTED_ALGORITHM, SELECTED_TYPE>/2000/21",
      "run_name": "merge_vec<SELECTED_ALGORITHM, SELECTED_TYPE>/2000/21",
      "run_type": "iteration",
      "repetitions": 0,
      "repetition_index": 0,
      "threads": 1,
      "iterations": 685193,
      "real_time": 1.0095378761895454e+03,
      "cpu_time": 1.0095196594244213e+03,
      "time_unit": "ns"
    },
    {
      "name": "merge_vec<SELECTED_ALGORITHM, SELECTED_TYPE>/2000/22",
      "run_name": "merge_vec<SELECTED_ALGORITHM, SELECTED_TYPE>/2000/22",
      "run_type": "iteration",
      "repetitions": 0,
      "repetition_index": 0,
      "threads": 1,
      "iterations": 586880,
      "real_time": 1.1934810489367799e+03,
      "cpu_time": 1.1934730421892068e+03,
      "time_unit": "ns"
    },
    {
      "name": "merge_vec<SELECTED_ALGORITHM, SELECTED_TYPE>/2000/23",
      "run_name": "merge_vec<SELECTED_ALGORITHM, SELECTED_TYPE>/2000/23",
      "run_type": "iteration",
      "repetitions": 0,
      "repetition_index": 0,
      "threads": 1,
      "iterations": 614752,
      "real_time": 1.1550325562177247e+03,
      "cpu_time": 1.1550122862552714e+03,
      "time_unit": "ns"
    },
    {
      "name": "merge_vec<SELECTED_ALGORITHM, SELECTED_TYPE>/2000/24",
      "run_name": "merge_vec<SELECTED_ALGORITHM, SELECTED_TYPE>/2000/24",
      "run_type": "iteration",
      "repetitions": 0,
      "repetition_index": 0,
      "threads": 1,
      "iterations": 544985,
      "real_time": 1.2341422351073020e+03,
      "cpu_time": 1.2341283227978763e+03,
      "time_unit": "ns"
    },
    {
      "name": "merge_vec<SELECTED_ALGORITHM, SELECTED_TYPE>/2000/25",
      "run_name": "merge_vec<SELECTED_ALGORITHM, SELECTED_TYPE>/2000/25",
      "run_type": "iteration",
      "repetitions": 0,
      "repetition_index": 0,
      "threads": 1,
      "iterations": 526984,
      "real_time": 1.2401917420641992e+03,
      "cpu_time": 1.2401861232978595e+03,
      "time_unit": "ns"
    },
    {
      "name": "merge_vec<SELECTED_ALGORITHM, SELECTED_TYPE>/2000/26",
      "run_name": "merge_vec<SELECTED_ALGORITHM, SELECTED_TYPE>/2000/26",
      "run_type": "iteration",
      "repetitions": 0,
      "repetition_index": 0,
      "threads": 1,
      "iterations": 554377,
      "real_time": 1.2327793956098485e+03,
      "cpu_time": 1.2327778912184299e+03,
      "time_unit": "ns"
    },
    {
      "name": "merge_vec<SELECTED_ALGORITHM, SELECTED_TYPE>/2000/27",
      "run_name": "merge_vec<SELECTED_ALGORITHM, SELECTED_TYPE>/2000/27",
      "run_type": "iteration",
      "repetitions": 0,
      "repetition_index": 0,
      "threads": 1,
      "iterations": 500551,
      "real_time": 1.3591099008888914e+03,
      "cpu_time": 1.3591023651935554e+03,
      "time_unit": "ns"
    },
    {
      "name": "merge_vec<SELECTED_ALGORITHM, SELECTED_TYPE>/2000/28",
      "run_name": "merge_vec<SELECTED_ALGORITHM, SELECTED_TYPE>/2000/28",
      "run_type": "iteration",
      "repetitions": 0,
      "repetition_index": 0,
      "threads": 1,
      "iterations": 519206,
      "real_time": 1.3431969757665886e+03,
      "cpu_time": 1.3431766331668018e+03,
      "time_unit": "ns"
    },
    {
      "name": "merge_vec<SELECTED_ALGORITHM, SELECTED_TYPE>/2000/29",
      "run_name": "merge_vec<SELECTED_ALGORITHM, SELECTED_TYPE>/2000/29",
      "run_type": "iteration",
      "repetitions": 0,
      "repetition_index": 0,
      "threads": 1,
      "iterations": 507727,
      "real_time": 1.3496549523660551e+03,
      "cpu_time": 1.3496436490476187e+03,
      "time_unit": "ns"
    },
    {
      "name": "merge_vec<SELECTED_ALGORITHM, SELECTED_TYPE>/2000/30",
      "run_name": "merge_vec<SELECTED_ALGORITHM, SELECTED_TYPE>/2000/30",
      "run_type": "iteration",
      "repetitions": 0,
      "repetition_index": 0,
      "threads": 1,
      "iterations": 518755,
      "real_time": 1.3340947036656896e+03,
      "cpu_time": 1.3340837659396088e+03,
      "time_unit": "ns"
    },
    {
      "name": "merge_vec<SELECTED_ALGORITHM, SELECTED_TYPE>/2000/31",
      "run_name": "merge_vec<SELECTED_ALGORITHM, SELECTED_TYPE>/2000/31",
      "run_type": "iteration",
      "repetitions": 0,
      "repetition_index": 0,
      "threads": 1,
      "iterations": 468705,
      "real_time": 1.3613569580013075e+03,
      "cpu_time": 1.3613552981086161e+03,
      "time_unit": "ns"
    },
    {
      "name": "merge_vec<SELECTED_ALGORITHM, SELECTED_TYPE>/2000/32",
      "run_name": "merge_vec<SELECTED_ALGORITHM, SELECTED_TYPE>/2000/32",
      "run_type": "iteration",
      "repetitions": 0,
      "repetition_index": 0,
      "threads": 1,
      "iterations": 471154,
      "real_time": 1.5055785114845953e+03,
      "cpu_time": 1.5055764420974879e+03,
      "time_unit": "ns"
    },
    {
      "name": "merge_vec<SELECTED_ALGORITHM, SELECTED_TYPE>/2000/33",
      "run_name": "merge_vec<SELECTED_ALGORITHM, SELECTED_TYPE>/2000/33",
      "run_type": "iteration",
      "repetitions": 0,
      "repetition_index": 0,
      "threads": 1,
      "iterations": 482405,
      "real_time": 1.3950584591787317e+03,
      "cpu_time": 1.3950412081135137e+03,
      "time_unit": "ns"
    },
    {
      "name": "merge_vec<SELECTED_ALGORITHM, SELECTED_TYPE>/2000/34",
      "run_name": "merge_vec<SELECTED_ALGORITHM, SELECTED_TYPE>/2000/34",
      "run_type": "iteration",
      "repetitions": 0,
      "repetition_index": 0,
      "threads": 1,
      "iterations": 464312,
      "real_time": 1.4597916121057722e+03,
      "cpu_time": 1.4597836713244519e+03,
      "time_unit": "ns"
    },
    {
      "name": "merge_vec<SELECTED_ALGORITHM, SELECTED_TYPE>/2000/35",
      "run_name": "merge_vec<SELECTED_ALGORITHM, SELECTED_TYPE>/2000/35",
      "run_type": "iteration",
      "repetitions": 0,
      "repetition_index": 0,
      "threads": 1,
      "iterations": 454783,
      "real_time": 1.5369276226243394e+03,
      "cpu_time": 1.5369047391833085e+03,
      "time_unit": "ns"
    },
    {
      "name": "merge_vec<SELECTED_ALGORITHM, SELECTED_TYPE>/2000/36",
      "run_name": "merge_vec<SELECTED_ALGORITHM, SELECTED_TYPE>/2000/36",
      "run_type": "iteration",
      "repetitions": 0,
      "repetition_index": 0,
      "threads": 1,
      "iterations": 441577,
      "real_time": 1.5700339714252793e+03,
      "cpu_time": 1.5700239029659565e+03,
      "time_unit": "ns"
    },
    {
      "name": "merge_vec<SELECTED_ALGORITHM, SELECTED_TYPE>/2000/37",
      "run_name": "merge_vec<SELECTED_ALGORITHM, SELECTED_TYPE>/2000/37",
      "run_type": "iteration",
      "repetitions": 0,
      "repetition_index": 0,
      "threads": 1,
      "iterations": 415094,
      "real_time": 1.5950450139004743e+03,
      "cpu_time": 1.5950244474745491e+03,
      "time_unit": "ns"
    },
    {
      "name": "merge_vec<SELECTED_ALGORITHM, SELECTED_TYPE>/2000/38",
      "run_name": "merge_vec<SELECTED_ALGORITHM, SELECTED_TYPE>/2000/38",
      "run_type": "iteration",
      "repetitions": 0,
      "repetition_index": 0,
      "threads": 1,
      "iterations": 400696,
      "real_time": 1.6779845843235807e+03,
      "cpu_time": 1.6779814697426486e+03,
      "time_unit": "ns"
    },
    {
      "name": "merge_vec<SELECTED_ALGORITHM, SELECTED_TYPE>/2000/39",
      "run_name": "merge_vec<SELECTED_ALGORITHM, SELECTED_TYPE>/2000/39",
      "run_type": "iteration",
      "repetitions": 0,
      "repetition_index": 0,
      "threads": 1,
      "iterations": 396307,
      "real_time": 1.7081559674698563e+03,
      "cpu_time": 1.7081525332633607e+03,
      "time_unit": "ns"
    },
    {
      "name": "merge_vec<SELECTED_ALGORITHM, SELECTED_TYPE>/2000/40",
      "run_name": "merge_vec<SELECTED_ALGORITHM, SELECTED_TYPE>/2000/40",
      "run_type": "iteration",
      "repetitions": 0,
      "repetition_index": 0,
      "threads": 1,
      "iterations": 396293,
      "real_time": 1.7271915829952206e+03,
      "cpu_time": 1.7271761297827463e+03,
      "time_unit": "ns"
    },
    {
      "name": "merge_vec<SELECTED_ALGORITHM, SELECTED_TYPE>/2000/41",
      "run_name": "merge_vec<SELECTED_ALGORITHM, SELECTED_TYPE>/2000/41",
      "run_type": "iteration",
      "repetitions": 0,
      "repetition_index": 0,
      "threads": 1,
      "iterations": 397705,
      "real_time": 1.7117138934633374e+03,
      "cpu_time": 1.7117096038521038e+03,
      "time_unit": "ns"
    },
    {
      "name": "merge_vec<SELECTED_ALGORITHM, SELECTED_TYPE>/2000/42",
      "run_name": "merge_vec<SELECTED_ALGORITHM, SELECTED_TYPE>/2000/42",
      "run_type": "iteration",
      "repetitions": 0,
      "repetition_index": 0,
      "threads": 1,
      "iterations": 383424,
      "real_time": 1.7584703487526299e+03,
      "cpu_time": 1.7584458067309201e+03,
      "time_unit": "ns"
    },
    {
      "name": "merge_vec<SELECTED_ALGORITHM, SELECTED_TYPE>/2000/43",
      "run_name": "merge_vec<SELECTED_ALGORITHM, SELECTED_TYPE>/2000/43",
      "run_type": "iteration",
      "repetitions": 0,
      "repetition_index": 0,
      "threads": 1,
      "iterations": 397913,
      "real_time": 1.7438705546189008e+03,
      "cpu_time": 1.7438614847969177e+03,
      "time_unit": "ns"
    },
    {
      "name": "merge_vec<SELECTED_ALGORITHM, SELECTED_TYPE>/2000/44",
      "run_name": "merge_vec<SELECTED_ALGORITHM, SELECTED_TYPE>/2000/44",
      "run_type": "iteration",
      "repetitions": 0,
      "repetition_index": 0,
      "threads": 1,
      "iterations": 395453,
      "real_time": 1.7509052479052777e+03,
      "cpu_time": 1.7508948825776965e+03,
      "time_unit": "ns"
    },
    {
      "name": "merge_vec<SELECTED_ALGORITHM, SELECTED_TYPE>/2000/45",
      "run_name": "merge_vec<SELECTED_ALGORITHM, SELECTED_TYPE>/2000/45",
      "run_type": "iteration",
      "repetitions": 0,
      "repetition_index": 0,
      "threads": 1,
      "iterations": 397682,
      "real_time": 1.7331123611326968e+03,
      "cpu_time": 1.7331009500052871e+03,
      "time_unit": "ns"
    },
    {
      "name": "merge_vec<SELECTED_ALGORITHM, SELECTED_TYPE>/2000/46",
      "run_name": "merge_vec<SELECTED_ALGORITHM, SELECTED_TYPE>/2000/46",
      "run_type": "iteration",
      "repetitions": 0,
      "repetition_index": 0,
      "threads": 1,
      "iterations": 403601,
      "real_time": 1.7090962881654423e+03,
      "cpu_time": 1.7090855647037545e+03,
      "time_unit": "ns"
    },
    {
      "name": "merge_vec<SELECTED_ALGORITHM, SELECTED_TYPE>/2000/47",
      "run_name": "merge_vec<SELECTED_ALGORITHM, SELECTED_TYPE>/2000/47",
      "run_type": "iteration",
      "repetitions": 0,
      "repetition_index": 0,
      "threads": 1,
      "iterations": 399436,
      "real_time": 1.7479372264889503e+03,
      "cpu_time": 1.7479310753161853e+03,
      "time_unit": "ns"
    },
    {
      "name": "merge_vec<SELECTED_ALGORITHM, SELECTED_TYPE>/2000/48",
      "run_name": "merge_vec<SELECTED_ALGORITHM, SELECTED_TYPE>/2000/48",
      "run_type": "iteration",
      "repetitions": 0,
      "repetition_index": 0,
      "threads": 1,
      "iterations": 380483,
      "real_time": 1.7915203359940151e+03,
      "cpu_time": 1.7915143357258960e+03,
      "time_unit": "ns"
    },
    {
      "name": "merge_vec<SELECTED_ALGORITHM, SELECTED_TYPE>/2000/49",
      "run_name": "merge_vec<SELECTED_ALGORITHM, SELECTED_TYPE>/2000/49",
      "run_type": "iteration",
      "repetitions": 0,
      "repetition_index": 0,
      "threads": 1,
      "iterations": 375394,
      "real_time": 1.7830538367688075e+03,
      "cpu_time": 1.7830474168473752e+03,
      "time_unit": "ns"
    },
    {
      "name": "merge_vec<SELECTED_ALGORITHM, SELECTED_TYPE>/2000/50",
      "run_name": "merge_vec<SELECTED_ALGORITHM, SELECTED_TYPE>/2000/50",
      "run_type": "iteration",
      "repetitions": 0,
      "repetition_index": 0,
      "threads": 1,
      "iterations": 392729,
      "real_time": 1.7548259334046702e+03,
      "cpu_time": 1.7548113915702622e+03,
      "time_unit": "ns"
    },
    {
      "name": "merge_vec<SELECTED_ALGORITHM, SELECTED_TYPE>/2000/51",
      "run_name": "merge_vec<SELECTED_ALGORITHM, SELECTED_TYPE>/2000/51",
      "run_type": "iteration",
      "repetitions": 0,
      "repetition_index": 0,
      "threads": 1,
      "iterations": 388554,
      "real_time": 1.7599423760915747e+03,
      "cpu_time": 1.7599151443557432e+03,
      "time_unit": "ns"
    },
    {
      "name": "merge_vec<SELECTED_ALGORITHM, SELECTED_TYPE>/2000/52",
      "run_name": "merge_vec<SELECTED_ALGORITHM, SELECTED_TYPE>/2000/52",
      "run_type": "iteration",
      "repetitions": 0,
      "repetition_index": 0,
      "threads": 1,
      "iterations": 401522,
      "real_time": 1.7154125402846103e+03,
      "cpu_time": 1.7153991362864385e+03,
      "time_unit": "ns"
    },
    {
      "name": "merge_vec<SELECTED_ALGORITHM, SELECTED_TYPE>/2000/53",
      "run_name": "merge_vec<SELECTED_ALGORITHM, SELECTED_TYPE>/2000/53",
      "run_type": "iteration",
      "repetitions": 0,
      "repetition_index": 0,
      "threads": 1,
      "iterations": 396522,
      "real_time": 1.7428683629152679e+03,
      "cpu_time": 1.7428573799183905e+03,
      "time_unit": "ns"
    },
    {
      "name": "merge_vec<SELECTED_ALGORITHM, SELECTED_TYPE>/2000/54",
      "run_name": "merge_vec<SELECTED_ALGORITHM, SELECTED_TYPE>/2000/54",
      "run_type": "iteration",
      "repetitions": 0,
      "repetition_index": 0,
      "threads": 1,
      "iterations": 398567,
      "real_time": 1.7111299154219607e+03,
      "cpu_time": 1.7111199597558366e+03,
      "time_unit": "ns"
    },
    {
      "name": "merge_vec<SELECTED_ALGORITHM, SELECTED_TYPE>/2000/55",
      "run_name": "merge_vec<SELECTED_ALGORITHM, SELECTED_TYPE>/2000/55",
      "run_type": "iteration",
      "repetitions": 0,
      "repetition_index": 0,
      "threads": 1,
      "iterations": 402087,
      "real_time": 1.7141200909253180e+03,
      "cpu_time": 1.7141160072322684e+03,
      "time_unit": "ns"
    },
    {
      "name": "merge_vec<SELECTED_ALGORITHM, SELECTED_TYPE>/2000/56",
      "run_name": "merge_vec<SELECTED_ALGORITHM, SELECTED_TYPE>/2000/56",
      "run_type": "iteration",
      "repetitions": 0,
      "repetition_index": 0,
      "threads": 1,
      "iterations": 403092,
      "real_time": 1.7168096340289705e+03,
      "cpu_time": 1.7168089021860994e+03,
      "time_unit": "ns"
    },
    {
      "name": "merge_vec<SELECTED_ALGORITHM, SELECTED_TYPE>/2000/57",
      "run_name": "merge_vec<SELECTED_ALGORITHM, SELECTED_TYPE>/2000/57",
      "run_type": "iteration",
      "repetitions": 0,
      "repetition_index": 0,
      "threads": 1,
      "iterations": 399669,
      "real_time": 1.6981840072663833e+03,
      "cpu_time": 1.6981772591819720e+03,
      "time_unit": "ns"
    },
    {
      "name": "merge_vec<SELECTED_ALGORITHM, SELECTED_TYPE>/2000/58",
      "run_name": "merge_vec<SELECTED_ALGORITHM, SELECTED_TYPE>/2000/58",
      "run_type": "iteration",
      "repetitions": 0,
      "repetition_index": 0,
      "threads": 1,
      "iterations": 410702,
      "real_time": 1.6726125463230539e+03,
      "cpu_time": 1.6726009418020924e+03,
      "time_unit": "ns"
    },
    {
      "name": "merge_vec<SELECTED_ALGORITHM, SELECTED_TYPE>/2000/59",
      "run_name": "merge_vec<SELECTED_ALGORITHM, SELECTED_TYPE>/2000/59",
      "run_type": "iteration",
      "repetitions": 0,
      "repetition_index": 0,
      "threads": 1,
      "iterations": 420416,
      "real_time": 1.6526217698663545e+03,
      "cpu_time": 1.6526074768800304e+03,
      "time_unit": "ns"
    },
    {
      "name": "merge_vec<SELECTED_ALGORITHM, SELECTED_TYPE>/2000/60",
      "run_name": "merge_vec<SELECTED_ALGORITHM, SELECTED_TYPE>/2000/60",
      "run_type": "iteration",
      "repetitions": 0,
      "repetition_index": 0,
      "threads": 1,
      "iterations": 422485,
      "real_time": 1.6413039113814880e+03,
      "cpu_time": 1.6412788241002504e+03,
      "time_unit": "ns"
    },
    {
      "name": "merge_vec<SELECTED_ALGORITHM, SELECTED_TYPE>/2000/61",
      "run_name": "merge_vec<SELECTED_ALGORITHM, SELECTED_TYPE>/2000/61",
      "run_type": "iteration",
      "repetitions": 0,
      "repetition_index": 0,
      "threads": 1,
      "iterations": 425856,
      "real_time": 1.5789172020590936e+03,
      "cpu_time": 1.5789145016155780e+03,
      "time_unit": "ns"
    },
    {
      "name": "merge_vec<SELECTED_ALGORITHM, SELECTED_TYPE>/2000/62",
      "run_name": "merge_vec<SELECTED_ALGORITHM, SELECTED_TYPE>/2000/62",
      "run_type": "iteration",
      "repetitions": 0,
      "repetition_index": 0,
      "threads": 1,
      "iterations": 418626,
      "real_time": 1.6082144587294831e+03,
      "cpu_time": 1.6082001691247049e+03,
      "time_unit": "ns"
    },
    {
      "name": "merge_vec<SELECTED_ALGORITHM, SELECTED_TYPE>/2000/63",
      "run_name": "merge_vec<SELECTED_ALGORITHM, SELECTED_TYPE>/2000/63",
      "run_type": "iteration",
      "repetitions": 0,
      "repetition_index": 0,
      "threads": 1,
      "iterations": 454560,
      "real_time": 1.4953216649065321e+03,
      "cpu_time": 1.4953200633579618e+03,
      "time_unit": "ns"
    },
    {
      "name": "merge_vec<SELECTED_ALGORITHM, SELECTED_TYPE>/2000/64",
      "run_name": "merge_vec<SELECTED_ALGORITHM, SELECTED_TYPE>/2000/64",
      "run_type": "iteration",
      "repetitions": 0,
      "repetition_index": 0,
      "threads": 1,
      "iterations": 455558,
      "real_time": 1.5272584610519971e+03,
      "cpu_time": 1.5272611742083327e+03,
      "time_unit": "ns"
    },
    {
      "name": "merge_vec<SELECTED_ALGORITHM, SELECTED_TYPE>/2000/65",
      "run_name": "merge_vec<SELECTED_ALGORITHM, SELECTED_TYPE>/2000/65",
      "run_type": "iteration",
      "repetitions": 0,
      "repetition_index": 0,
      "threads": 1,
      "iterations": 426770,
      "real_time": 1.5658296646907972e+03,
      "cpu_time": 1.5658181971553747e+03,
      "time_unit": "ns"
    },
    {
      "name": "merge_vec<SELECTED_ALGORITHM, SELECTED_TYPE>/2000/66",
      "run_name": "merge_vec<SELECTED_ALGORITHM, SELECTED_TYPE>/2000/66",
      "run_type": "iteration",
      "repetitions": 0,
      "repetition_index": 0,
      "threads": 1,
      "iterations": 465566,
      "real_time": 1.4520084864448097e+03,
      "cpu_time": 1.4519905147712705e+03,
      "time_unit": "ns"
    },
    {
      "name": "merge_vec<SELECTED_ALGORITHM, SELECTED_TYPE>/2000/67",
      "run_name": "merge_vec<SELECTED_ALGORITHM, SELECTED_TYPE>/2000/67",
      "run_type": "iteration",
      "repetitions": 0,
      "repetition_index": 0,
      "threads": 1,
      "iterations": 478758,
      "real_time": 1.4372121865326089e+03,
      "cpu_time": 1.4371945158096503e+03,
      "time_unit": "ns"
    },
    {
      "name": "merge_vec<SELECTED_ALGORITHM, SELECTED_TYPE>/2000/68",
      "run_name": "merge_vec<SELECTED_ALGORITHM, SELECTED_TYPE>/2000/68",
      "run_type": "iteration",
      "repetitions": 0,
      "repetition_index": 0,
      "threads": 1,
      "iterations": 454792,
      "real_time": 1.4694681282871882e+03,
      "cpu_time": 1.4694622860560387e+03,
      "time_unit": "ns"
    },
    {
      "name": "merge_vec<SELECTED_ALGORITHM, SELECTED_TYPE>/2000/69",
      "run_name": "merge_vec<SELECTED_ALGORITHM, SELECTED_TYPE>/2000/69",
      "run_type": "iteration",
      "repetitions": 0,
      "repetition_index": 0,
      "threads": 1,
      "iterations": 481965,
      "real_time": 1.4002155280983393e+03,
      "cpu_time": 1.4002063116616273e+03,
      "time_unit": "ns"
    },
    {
      "name": "merge_vec<SELECTED_ALGORITHM, SELECTED_TYPE>/2000/70",
      "run_name": "merge_vec<SELECTED_ALGORITHM, SELECTED_TYPE>/2000/70",
      "run_type": "iteration",
      "repetitions": 0,
      "repetition_index": 0,
      "threads": 1,
      "iterations": 483886,
      "real_time": 1.3775276656072256e+03,
      "cpu_time": 1.3775213397370367e+03,
      "time_unit": "ns"
    },
    {
      "name": "merge_vec<SELECTED_ALGORITHM, SELECTED_TYPE>/2000/71",
      "run_name": "merge_vec<SELECTED_ALGORITHM, SELECTED_TYPE>/2000/71",
      "run_type": "iteration",
      "repetitions": 0,
      "repetition_index": 0,
      "threads": 1,
      "iterations": 499378,
      "real_time": 1.3629354817395697e+03,
      "cpu_time": 1.3629412348962117e+03,
      "time_unit": "ns"
    },
    {
      "name": "merge_vec<SELECTED_ALGORITHM, SELECTED_TYPE>/2000/72",
      "run_name": "merge_vec<SELECTED_ALGORITHM, SELECTED_TYPE>/2000/72",
      "run_type": "iteration",
      "repetitions": 0,
      "repetition_index": 0,
      "threads": 1,
      "iterations": 485726,
      "real_time": 1.3743704804765055e+03,
      "cpu_time": 1.3743682261192532e+03,
      "time_unit": "ns"
    },
    {
      "name": "merge_vec<SELECTED_ALGORITHM, SELECTED_TYPE>/2000/73",
      "run_name": "merge_vec<SELECTED_ALGORITHM, SELECTED_TYPE>/2000/73",
      "run_type": "iteration",
      "repetitions": 0,
      "repetition_index": 0,
      "threads": 1,
      "iterations": 461145,
      "real_time": 1.4316923917638801e+03,
      "cpu_time": 1.4316799878563140e+03,
      "time_unit": "ns"
    },
    {
      "name": "merge_vec<SELECTED_ALGORITHM, SELECTED_TYPE>/2000/74",
      "run_name": "merge_vec<SELECTED_ALGORITHM, SELECTED_TYPE>/2000/74",
      "run_type": "iteration",
      "repetitions": 0,
      "repetition_index": 0,
      "threads": 1,
      "iterations": 535614,
      "real_time": 1.3056946961803490e+03,
      "cpu_time": 1.3056865354527747e+03,
      "time_unit": "ns"
    },
    {
      "name": "merge_vec<SELECTED_ALGORITHM, SELECTED_TYPE>/2000/75",
      "run_name": "merge_vec<SELECTED_ALGORITHM, SELECTED_TYPE>/2000/75",
      "run_type": "iteration",
      "repetitions": 0,
      "repetition_index": 0,
      "threads": 1,
      "iterations": 510529,
      "real_time": 1.3295839158991625e+03,
      "cpu_time": 1.3295724571963678e+03,
      "time_unit": "ns"
    },
    {
      "name": "merge_vec<SELECTED_ALGORITHM, SELECTED_TYPE>/2000/76",
      "run_name": "merge_vec<SELECTED_ALGORITHM, SELECTED_TYPE>/2000/76",
      "run_type": "iteration",
      "repetitions": 0,
      "repetition_index": 0,
      "threads": 1,
      "iterations": 536418,
      "real_time": 1.2878255912365628e+03,
      "cpu_time": 1.2878177335585337e+03,
      "time_unit": "ns"
    },
    {
      "name": "merge_vec<SELECTED_ALGORITHM, SELECTED_TYPE>/2000/77",
      "run_name": "merge_vec<SELECTED_ALGORITHM, SELECTED_TYPE>/2000/77",
      "run_type": "iteration",
      "repetitions": 0,
      "repetition_index": 0,
      "threads": 1,
      "iterations": 537093,
      "real_time": 1.2862701264027628e+03,
      "cpu_time": 1.2862529636394595e+03,
      "time_unit": "ns"
    },
    {
      "name": "merge_vec<SELECTED_ALGORITHM, SELECTED_TYPE>/2000/78",
      "run_name": "merge_vec<SELECTED_ALGORITHM, SELECTED_TYPE>/2000/78",
      "run_type": "iteration",
      "repetitions": 0,
      "repetition_index": 0,
      "threads": 1,
      "iterations": 538223,
      "real_time": 1.2640347105195440e+03,
      "cpu_time": 1.2640241275456472e+03,
      "time_unit": "ns"
    },
    {
      "name": "merge_vec<SELECTED_ALGORITHM, SELECTED_TYPE>/2000/79",
      "run_name": "merge_vec<SELECTED_ALGORITHM, SELECTED_TYPE>/2000/79",
      "run_type": "iteration",
      "repetitions": 0,
      "repetition_index": 0,
      "threads": 1,
      "iterations": 533510,
      "real_time": 1.2693579670483489e+03,
      "cpu_time": 1.2693488163296065e+03,
      "time_unit": "ns"
    },
    {
      "name": "merge_vec<SELECTED_ALGORITHM, SELECTED_TYPE>/2000/80",
      "run_name": "merge_vec<SELECTED_ALGORITHM, SELECTED_TYPE>/2000/80",
      "run_type": "iteration",
      "repetitions": 0,
      "repetition_index": 0,
      "threads": 1,
      "iterations": 579560,
      "real_time": 1.3620354424046118e+03,
      "cpu_time": 1.3620299123472801e+03,
      "time_unit": "ns"
    },
    {
      "name": "merge_vec<SELECTED_ALGORITHM, SELECTED_TYPE>/2000/81",
      "run_name": "merge_vec<SELECTED_ALGORITHM, SELECTED_TYPE>/2000/81",
      "run_type": "iteration",
      "repetitions": 0,
      "repetition_index": 0,
      "threads": 1,
      "iterations": 531933,
      "real_time": 1.2248061297190991e+03,
      "cpu_time": 1.2248010407325817e+03,
      "time_unit": "ns"
    },
    {
      "name": "merge_vec<SELECTED_ALGORITHM, SELECTED_TYPE>/2000/82",
      "run_name": "merge_vec<SELECTED_ALGORITHM, SELECTED_TYPE>/2000/82",
      "run_type": "iteration",
      "repetitions": 0,
      "repetition_index": 0,
      "threads": 1,
      "iterations": 560405,
      "real_time": 1.2300884289041587e+03,
      "cpu_time": 1.2300867265638349e+03,
      "time_unit": "ns"
    },
    {
      "name": "merge_vec<SELECTED_ALGORITHM, SELECTED_TYPE>/2000/83",
      "run_name": "merge_vec<SELECTED_ALGORITHM, SELECTED_TYPE>/2000/83",
      "run_type": "iteration",
      "repetitions": 0,
      "repetition_index": 0,
      "threads": 1,
      "iterations": 571775,
      "real_time": 1.2303337501643225e+03,
      "cpu_time": 1.2303287831751982e+03,
      "time_unit": "ns"
    },
    {
      "name": "merge_vec<SELECTED_ALGORITHM, SELECTED_TYPE>/2000/84",
      "run_name": "merge_vec<SELECTED_ALGORITHM, SELECTED_TYPE>/2000/84",
      "run_type": "iteration",
      "repetitions": 0,
      "repetition_index": 0,
      "threads": 1,
      "iterations": 565543,
      "real_time": 1.1948107659367024e+03,
      "cpu_time": 1.1947994140145086e+03,
      "time_unit": "ns"
    },
    {
      "name": "merge_vec<SELECTED_ALGORITHM, SELECTED_TYPE>/2000/85",
      "run_name": "merge_vec<SELECTED_ALGORITHM, SELECTED_TYPE>/2000/85",
      "run_type": "iteration",
      "repetitions": 0,
      "repetition_index": 0,
      "threads": 1,
      "iterations": 569294,
      "real_time": 1.2043891943353690e+03,
      "cpu_time": 1.2043725579401921e+03,
      "time_unit": "ns"
    },
    {
      "name": "merge_vec<SELECTED_ALGORITHM, SELECTED_TYPE>/2000/86",
      "run_name": "merge_vec<SELECTED_ALGORITHM, SELECTED_TYPE>/2000/86",
      "run_type": "iteration",
      "repetitions": 0,
      "repetition_index": 0,
      "threads": 1,
      "iterations": 546368,
      "real_time": 1.2774281839344278e+03,
      "cpu_time": 1.2774156740511989e+03,
      "time_unit": "ns"
    },
    {
      "name": "merge_vec<SELECTED_ALGORITHM, SELECTED_TYPE>/2000/87",
      "run_name": "merge_vec<SELECTED_ALGORITHM, SELECTED_TYPE>/2000/87",
      "run_type": "iteration",
      "repetitions": 0,
      "repetition_index": 0,
      "threads": 1,
      "iterations": 546594,
      "real_time": 1.2759709162557178e+03,
      "cpu_time": 1.2759560789177990e+03,
      "time_unit": "ns"
    },
    {
      "name": "merge_vec<SELECTED_ALGORITHM, SELECTED_TYPE>/2000/88",
      "run_name": "merge_vec<SELECTED_ALGORITHM, SELECTED_TYPE>/2000/88",
      "run_type": "iteration",
      "repetitions": 0,
      "repetition_index": 0,
      "threads": 1,
      "iterations": 518080,
      "real_time": 1.3440717746294424e+03,
      "cpu_time": 1.3440675687152584e+03,
      "time_unit": "ns"
    },
    {
      "name": "merge_vec<SELECTED_ALGORITHM, SELECTED_TYPE>/2000/89",
      "run_name": "merge_vec<SELECTED_ALGORITHM, SELECTED_TYPE>/2000/89",
      "run_type": "iteration",
      "repetitions": 0,
      "repetition_index": 0,
      "threads": 1,
      "iterations": 518944,
      "real_time": 1.3455544548158580e+03,
      "cpu_time": 1.3455522503391385e+03,
      "time_unit": "ns"
    },
    {
      "name": "merge_vec<SELECTED_ALGORITHM, SELECTED_TYPE>/2000/90",
      "run_name": "merge_vec<SELECTED_ALGORITHM, SELECTED_TYPE>/2000/90",
      "run_type": "iteration",
      "repetitions": 0,
      "repetition_index": 0,
      "threads": 1,
      "iterations": 497588,
      "real_time": 1.4005049398296876e+03,
      "cpu_time": 1.4004946602410221e+03,
      "time_unit": "ns"
    },
    {
      "name": "merge_vec<SELECTED_ALGORITHM, SELECTED_TYPE>/2000/91",
      "run_name": "merge_vec<SELECTED_ALGORITHM, SELECTED_TYPE>/2000/91",
      "run_type": "iteration",
      "repetitions": 0,
      "repetition_index": 0,
      "threads": 1,
      "iterations": 510297,
      "real_time": 1.3710486167860720e+03,
      "cpu_time": 1.3710349619926999e+03,
      "time_unit": "ns"
    },
    {
      "name": "merge_vec<SELECTED_ALGORITHM, SELECTED_TYPE>/2000/92",
      "run_name": "merge_vec<SELECTED_ALGORITHM, SELECTED_TYPE>/2000/92",
      "run_type": "iteration",
      "repetitions": 0,
      "repetition_index": 0,
      "threads": 1,
      "iterations": 496327,
      "real_time": 1.4197282114409848e+03,
      "cpu_time": 1.4197126712832371e+03,
      "time_unit": "ns"
    },
    {
      "name": "merge_vec<SELECTED_ALGORITHM, SELECTED_TYPE>/2000/93",
      "run_name": "merge_vec<SELECTED_ALGORITHM, SELECTED_TYPE>/2000/93",
      "run_type": "iteration",
      "repetitions": 0,
      "repetition_index": 0,
      "threads": 1,
      "iterations": 472327,
      "real_time": 1.4678782368994482e+03,
      "cpu_time": 1.4678588668443649e+03,
      "time_unit": "ns"
    },
    {
      "name": "merge_vec<SELECTED_ALGORITHM, SELECTED_TYPE>/2000/94",
      "run_name": "merge_vec<SELECTED_ALGORITHM, SELECTED_TYPE>/2000/94",
      "run_type": "iteration",
      "repetitions": 0,
      "repetition_index": 0,
      "threads": 1,
      "iterations": 501538,
      "real_time": 1.3861652018391512e+03,
      "cpu_time": 1.3861567717700264e+03,
      "time_unit": "ns"
    },
    {
      "name": "merge_vec<SELECTED_ALGORITHM, SELECTED_TYPE>/2000/95",
      "run_name": "merge_vec<SELECTED_ALGORITHM, SELECTED_TYPE>/2000/95",
      "run_type": "iteration",
      "repetitions": 0,
      "repetition_index": 0,
      "threads": 1,
      "iterations": 508294,
      "real_time": 1.3549132155798443e+03,
      "cpu_time": 1.3549024619610063e+03,
      "time_unit": "ns"
    },
    {
      "name": "merge_vec<SELECTED_ALGORITHM, SELECTED_TYPE>/2000/96",
      "run_name": "merge_vec<SELECTED_ALGORITHM, SELECTED_TYPE>/2000/96",
      "run_type": "iteration",
      "repetitions": 0,
      "repetition_index": 0,
      "threads": 1,
      "iterations": 516354,
      "real_time": 1.3604560321020936e+03,
      "cpu_time": 1.3604451771459183e+03,
      "time_unit": "ns"
    },
    {
      "name": "merge_vec<SELECTED_ALGORITHM, SELECTED_TYPE>/2000/97",
      "run_name": "merge_vec<SELECTED_ALGORITHM, SELECTED_TYPE>/2000/97",
      "run_type": "iteration",
      "repetitions": 0,
      "repetition_index": 0,
      "threads": 1,
      "iterations": 569972,
      "real_time": 1.2282527685570442e+03,
      "cpu_time": 1.2282398047623496e+03,
      "time_unit": "ns"
    },
    {
      "name": "merge_vec<SELECTED_ALGORITHM, SELECTED_TYPE>/2000/98",
      "run_name": "merge_vec<SELECTED_ALGORITHM, SELECTED_TYPE>/2000/98",
      "run_type": "iteration",
      "repetitions": 0,
      "repetition_index": 0,
      "threads": 1,
      "iterations": 592286,
      "real_time": 1.1929757245654871e+03,
      "cpu_time": 1.1929632846293778e+03,
      "time_unit": "ns"
    },
    {
      "name": "merge_vec<SELECTED_ALGORITHM, SELECTED_TYPE>/2000/99",
      "run_name": "merge_vec<SELECTED_ALGORITHM, SELECTED_TYPE>/2000/99",
      "run_type": "iteration",
      "repetitions": 0,
      "repetition_index": 0,
      "threads": 1,
      "iterations": 695638,
      "real_time": 9.9919553273368092e+02,
      "cpu_time": 9.9918444075798982e+02,
      "time_unit": "ns"
    },
    {
      "name": "merge_vec<SELECTED_ALGORITHM, SELECTED_TYPE>/2000/100",
      "run_name": "merge_vec<SELECTED_ALGORITHM, SELECTED_TYPE>/2000/100",
      "run_type": "iteration",
      "repetitions": 0,
      "repetition_index": 0,
      "threads": 1,
      "iterations": 11330751,
      "real_time": 6.1353374988125147e+01,
      "cpu_time": 6.1352881640413983e+01,
      "time_unit": "ns"
    }
  ]
}
